vin/__about__.py
vin/__init__.py
vin/constants.py
vin/database.py
vin/vehicle.db
vin-0.6.2.dist-info/METADATA
vin-0.6.2.dist-info/WHEEL
vin-0.6.2.dist-info/licenses/LICENSE.txt
vin-0.6.2.dist-info/RECORD
