Metadata-Version: 2.3
Name: vin
Version: 0.6.2
Summary: Vehicle Identification Number
Project-URL: Documentation, https://vin.readthedocs.io/en/latest/index.html
Project-URL: Issues, https://github.com/davidpeckham/vin/issues
Project-URL: Source, https://github.com/davidpeckham/vin
Author-email: David Peckham <dave.peckham@icloud.com>
License-Expression: MIT
License-File: LICENSE.txt
Keywords: nhtsa,vehicle,vin
Classifier: Development Status :: 4 - Beta
Classifier: Programming Language :: Python
Classifier: Programming Language :: Python :: 3.10
Classifier: Programming Language :: Python :: 3.11
Classifier: Programming Language :: Python :: 3.12
Classifier: Programming Language :: Python :: Implementation :: CPython
Classifier: Programming Language :: Python :: Implementation :: PyPy
Requires-Python: >=3.10
